Metadata-Version: 2.1
Name: drf-shortcuts
Version: 0.0.2
Summary: Common shortcuts for speeding up your development based on Django REST Framework (DRF).
Home-page: https://github.com/megaden/drf-shortcuts
Author: Daniel Ivanov
Author-email: megaden4eg@gmail.com
License: MIT
Platform: UNKNOWN
Classifier: Development Status :: 4 - Beta
Classifier: Intended Audience :: Developers
Classifier: Natural Language :: English
Classifier: License :: OSI Approved :: MIT License
Classifier: Programming Language :: Python
Classifier: Programming Language :: Python :: 3
Classifier: Programming Language :: Python :: 3.6
